tipi99/TP_model/TP_model_core_250225.py
tipi99/TP_model/my_serial/my_serial_250213.py
tipi99/TP_model/my_time/my_time_241007.py
tipi99/TP_view/Calendar_Elapsed_250401.py
tipi99/TP_view/Frame_1_graph_241118.py
tipi99/TP_view/Frame_1_graph_2_axis_250402.py
tipi99/TP_view/Frame_1_graph_2_axis_250402.py.bak
tipi99/TP_view/about_250225.py
tipi99/TP_view/commands_250401.py
tipi99/TP_view/commands_plot_250402.py
tipi99/TP_view/logo_CP.jpg
tipi99/TP_view/logo_CP_Scaled.png
tipi99/TP_view/logo_IMPMC.jpg
tipi99/TP_view/logo_IMPMC_Scaled.png
tipi99/TP_view/pop_up_241029.py
tipi99/TP_view/table_250401.py
tipi99/example/Example.csv
tipi99/example/Example.npy
tipi99/example/Example.txt
tipi99/tipi99.py
tipi99-0.0.2.dist-info/METADATA
tipi99-0.0.2.dist-info/WHEEL
tipi99-0.0.2.dist-info/entry_points.txt
tipi99-0.0.2.dist-info/RECORD
