Metadata-Version: 2.3
Name: tipi99
Version: 0.0.2
Summary: Graphical user interface to configure the Autonomous Temperature Pressure Sensor TP99 and download the registered data
License: GPL-3.0-or-later
Keywords: deep-sea sensor,temperature pressure sensor
Author: Yiuri GARINO
Author-email: yiuri.garino@cnrs.fr
Requires-Python: >=3.10
Classifier: License :: OSI Approved :: GNU General Public License v3 or later (GPLv3+)
Classifier: Programming Language :: Python :: 3
Classifier: Programming Language :: Python :: 3.10
Classifier: Programming Language :: Python :: 3.11
Classifier: Programming Language :: Python :: 3.12
Classifier: Programming Language :: Python :: 3.13
Requires-Dist: configparser (>=7.1.0,<8.0.0)
Requires-Dist: lmfit (>=1.3.2,<2.0.0)
Requires-Dist: matplotlib (>=3.10.0,<4.0.0)
Requires-Dist: numpy (>=2.2.3,<3.0.0)
Requires-Dist: pathlib (>=1.0.1,<2.0.0)
Requires-Dist: pyqt5 (>=5.15.11,<6.0.0)
Requires-Dist: pyserial (>=3.5,<4.0)
Project-URL: Repository, https://github.com/CelluleProjet/TiPi99
